openedx_course_export/__init__.py
openedx_course_export/apps.py
openedx_course_export/constants.py
openedx_course_export/s3_client.py
openedx_course_export/tasks.py
openedx_course_export/urls.py
openedx_course_export/utils.py
openedx_course_export/views.py
openedx_course_export/settings/__init__.py
openedx_course_export/settings/common.py
openedx_course_export/settings/production.py
openedx_course_export-0.1.4.dist-info/LICENSE.txt
openedx_course_export-0.1.4.dist-info/METADATA
openedx_course_export-0.1.4.dist-info/WHEEL
openedx_course_export-0.1.4.dist-info/entry_points.txt
openedx_course_export-0.1.4.dist-info/top_level.txt
openedx_course_export-0.1.4.dist-info/RECORD
