Metadata-Version: 2.1
Name: openedx-course-export
Version: 0.1.4
Summary: A django app plugin to add a new API to Open edX to export courses to S3 buckets
Home-page: https://github.com/openedx/openedx_course_export
Author: edX
Author-email: oscm@edx.org
Classifier: Development Status :: 3 - Alpha
Classifier: Framework :: Django
Classifier: Framework :: Django :: 3.2
Classifier: Intended Audience :: Developers
Classifier: License :: OSI Approved :: GNU Affero General Public License v3 or later (AGPLv3+)
Classifier: Natural Language :: English
Classifier: Programming Language :: Python :: 3
Classifier: Programming Language :: Python :: 3.5
Requires-Python: >=3.5
License-File: LICENSE.txt
Requires-Dist: Django
